jadio_long_term_memory/__init__.py
jadio_long_term_memory/ai/__init__.py
jadio_long_term_memory/cli/__init__.py
jadio_long_term_memory/cli/clicommands.json
jadio_long_term_memory/cli/main.py
jadio_long_term_memory/cli/run.py
jadio_long_term_memory/core/__init__.py
jadio_long_term_memory-0.0.1.dist-info/METADATA
jadio_long_term_memory-0.0.1.dist-info/WHEEL
jadio_long_term_memory-0.0.1.dist-info/licenses/LICENSE
jadio_long_term_memory-0.0.1.dist-info/RECORD
